README.txt
setup.py
docs/HISTORY.txt
docs/INSTALL.txt
docs/LICENSE.GPL
docs/LICENSE.txt
fourdigits/__init__.py
fourdigits.portlet.twitter.egg-info/PKG-INFO
fourdigits.portlet.twitter.egg-info/SOURCES.txt
fourdigits.portlet.twitter.egg-info/dependency_links.txt
fourdigits.portlet.twitter.egg-info/entry_points.txt
fourdigits.portlet.twitter.egg-info/namespace_packages.txt
fourdigits.portlet.twitter.egg-info/not-zip-safe
fourdigits.portlet.twitter.egg-info/requires.txt
fourdigits.portlet.twitter.egg-info/top_level.txt
fourdigits/portlet/__init__.py
fourdigits/portlet/twitter/__init__.py
fourdigits/portlet/twitter/configure.zcml
fourdigits/portlet/twitter/fourdigitsportlettwitter.pt
fourdigits/portlet/twitter/fourdigitsportlettwitter.py
fourdigits/portlet/twitter/twitter.py
fourdigits/portlet/twitter/version.txt
fourdigits/portlet/twitter/browser/__init__.py
fourdigits/portlet/twitter/browser/configure.zcml
fourdigits/portlet/twitter/browser/stylesheets/twitterportlet.css
fourdigits/portlet/twitter/locales/README.txt
fourdigits/portlet/twitter/locales/fourdigits.portlet.twitter.pot
fourdigits/portlet/twitter/locales/nl/LC_MESSAGES/fourdigits.portlet.twitter.po
fourdigits/portlet/twitter/locales/pt_BR/LC_MESSAGES/fourdigits.portlet.twitter.po
fourdigits/portlet/twitter/profiles/default/cssregistry.xml
fourdigits/portlet/twitter/profiles/default/metadata.xml
fourdigits/portlet/twitter/profiles/default/portlets.xml