Metadata-Version: 1.0
Name: fourdigits.portlet.twitter
Version: 0.8
Summary: Twitter portlet with multi search, filter, language                  filter functionality and number limiter
Home-page: http://plone.org/products/fourdigits.portlet.twitter
Author: Ralph Jacobs
Author-email: ralph@fourdigits.nl
License: GPL
Keywords: social media twitter 2.0
Platform: UNKNOWN
Classifier: Framework :: Plone
Classifier: Programming Language :: Python
